qtmonitor/__init__.py
qtmonitor/base.py
qtmonitor/example.py
qtmonitor/group.py
qtmonitor/monitor.py
qtmonitor/value.py
qtmonitor-0.2.0.dist-info/LICENSE
qtmonitor-0.2.0.dist-info/METADATA
qtmonitor-0.2.0.dist-info/WHEEL
qtmonitor-0.2.0.dist-info/top_level.txt
qtmonitor-0.2.0.dist-info/RECORD
