Metadata-Version: 2.1
Name: qtmonitor
Version: 0.2.0
Summary: Simple tool for creating a Qt-Dialog with updating values
Home-page: https://gitlab.com/ndeedy/qtmonitor
Author: Dietmar Kreider
Author-email: ndeedy@me.com
License: MIT
Project-URL: Homepage, https://gitlab.com/ndeedy/qtmonitor
Project-URL: Repository, https://gitlab.com/ndeedy/qtmonitor
Keywords: Qt,PySide2,Monitor,Debugging,Robotics
Platform: UNKNOWN
Classifier: Development Status :: 4 - Beta
Classifier: Intended Audience :: Developers
Classifier: Programming Language :: Python
Classifier: Programming Language :: Python :: 3.7
Classifier: License :: OSI Approved :: MIT License
Requires-Python: >=3.7
Requires-Dist: PySide2
